extypes/__init__.py
extypes/base.py
extypes/compat.py
extypes/django.py
extypes-2.0.0.dist-info/METADATA
extypes-2.0.0.dist-info/WHEEL
extypes-2.0.0.dist-info/top_level.txt
extypes-2.0.0.dist-info/RECORD
