Metadata-Version: 2.1
Name: extypes
Version: 2.0.0
Summary: Enhancements over Python's standard types
Home-page: https://github.com/rbarrois/extypes
Author: Raphaël Barrois
Author-email: raphael.barrois+extypes@polytechnique.org
License: BSD
Keywords: types,datastructure,structure
Platform: UNKNOWN
Classifier: Development Status :: 5 - Production/Stable
Classifier: Intended Audience :: Developers
Classifier: License :: OSI Approved :: BSD License
Classifier: Operating System :: OS Independent
Classifier: Programming Language :: Python :: 3.5
Classifier: Programming Language :: Python :: 3.6
Classifier: Programming Language :: Python :: 3.7
Classifier: Topic :: Software Development :: Libraries :: Python Modules
